redis_db_rafaeltovar/__init__.py
redis_db_rafaeltovar/db.py
redis_db_rafaeltovar-0.0.6.dist-info/licenses/LICENSE
redis_db_rafaeltovar-0.0.6.dist-info/METADATA
redis_db_rafaeltovar-0.0.6.dist-info/WHEEL
redis_db_rafaeltovar-0.0.6.dist-info/top_level.txt
redis_db_rafaeltovar-0.0.6.dist-info/RECORD
