Metadata-Version: 2.4
Name: redis-db-rafaeltovar
Version: 0.0.6
Summary: Python client for Redis database and key-value store
Author-email: Rafa <author@example.com>
License-Expression: MIT
Project-URL: Homepage, https://gitlab.com/rafaeltovar/tmp-redis
Project-URL: Issues, https://gitlab.com/rafaeltovar/tmp-redis/issues
Classifier: Programming Language :: Python :: 3
Classifier: Operating System :: OS Independent
Requires-Python: >=3.9
License-File: LICENSE
Dynamic: license-file
